[{"region":"FRA","totalVolume":92538927,"rowCount":74704,"alarmCount":101157,"siteCount":206,"detectorCount":32,"averageDetectorVolume":2891841.46875,"completeRecordRate":1},{"region":"GRE","totalVolume":85168504,"rowCount":68358,"alarmCount":383385,"siteCount":189,"detectorCount":32,"averageDetectorVolume":2661515.75,"completeRecordRate":0.9998037293854901},{"region":"WV2","totalVolume":77149320,"rowCount":53984,"alarmCount":124391,"siteCount":146,"detectorCount":32,"averageDetectorVolume":2410916.25,"completeRecordRate":1},{"region":"MEN","totalVolume":73268721,"rowCount":63056,"alarmCount":116124,"siteCount":179,"detectorCount":32,"averageDetectorVolume":2289647.53125,"completeRecordRate":1},{"region":"GEE","totalVolume":72181057,"rowCount":81788,"alarmCount":202502,"siteCount":242,"detectorCount":32,"averageDetectorVolume":2255658.03125,"completeRecordRate":1},{"region":"BBN","totalVolume":71543057,"rowCount":50036,"alarmCount":270961,"siteCount":143,"detectorCount":32,"averageDetectorVolume":2235720.53125,"completeRecordRate":1},{"region":"SPR","totalVolume":70742901,"rowCount":55888,"alarmCount":118319,"siteCount":157,"detectorCount":32,"averageDetectorVolume":2210715.65625,"completeRecordRate":1},{"region":"CRN","totalVolume":68151493,"rowCount":60592,"alarmCount":55224,"siteCount":168,"detectorCount":32,"averageDetectorVolume":2129734.15625,"completeRecordRate":1},{"region":"ESS","totalVolume":64836896,"rowCount":52584,"alarmCount":136120,"siteCount":154,"detectorCount":32,"averageDetectorVolume":2026153,"completeRecordRate":1},{"region":"GLI","totalVolume":64365497,"rowCount":38416,"alarmCount":86899,"siteCount":108,"detectorCount":32,"averageDetectorVolume":2011421.78125,"completeRecordRate":1},{"region":"ES2","totalVolume":61706214,"rowCount":40502,"alarmCount":240819,"siteCount":118,"detectorCount":32,"averageDetectorVolume":1928319.1875,"completeRecordRate":1},{"region":"DON","totalVolume":60323703,"rowCount":49224,"alarmCount":214418,"siteCount":137,"detectorCount":32,"averageDetectorVolume":1885115.71875,"completeRecordRate":1},{"region":"FT2","totalVolume":60303328,"rowCount":47334,"alarmCount":28443,"siteCount":138,"detectorCount":32,"averageDetectorVolume":1884479,"completeRecordRate":0.9992559523809523},{"region":"WV1","totalVolume":59715248,"rowCount":49504,"alarmCount":104690,"siteCount":141,"detectorCount":32,"averageDetectorVolume":1866101.5,"completeRecordRate":0.9992559523809523},{"region":"FT3","totalVolume":59227629,"rowCount":55412,"alarmCount":337160,"siteCount":162,"detectorCount":32,"averageDetectorVolume":1850863.40625,"completeRecordRate":1},{"region":"MC2","totalVolume":58988120,"rowCount":36344,"alarmCount":76259,"siteCount":105,"detectorCount":32,"averageDetectorVolume":1843378.75,"completeRecordRate":1},{"region":"SK2","totalVolume":58531444,"rowCount":44684,"alarmCount":136703,"siteCount":129,"detectorCount":32,"averageDetectorVolume":1829107.625,"completeRecordRate":0.9999309969265658},{"region":"PRS","totalVolume":57381694,"rowCount":41384,"alarmCount":74406,"siteCount":119,"detectorCount":32,"averageDetectorVolume":1793177.9375,"completeRecordRate":1},{"region":"FT1","totalVolume":56606500,"rowCount":54964,"alarmCount":184432,"siteCount":162,"detectorCount":32,"averageDetectorVolume":1768953.125,"completeRecordRate":1},{"region":"PR2","totalVolume":53218513,"rowCount":42784,"alarmCount":317994,"siteCount":122,"detectorCount":32,"averageDetectorVolume":1663078.53125,"completeRecordRate":1},{"region":"CA1","totalVolume":52698013,"rowCount":44800,"alarmCount":184776,"siteCount":128,"detectorCount":32,"averageDetectorVolume":1646812.90625,"completeRecordRate":1},{"region":"SP2","totalVolume":51829868,"rowCount":42704,"alarmCount":115268,"siteCount":118,"detectorCount":32,"averageDetectorVolume":1619683.375,"completeRecordRate":0.9995550768077932},{"region":"VIC","totalVolume":51768925,"rowCount":76818,"alarmCount":430404,"siteCount":222,"detectorCount":32,"averageDetectorVolume":1617778.90625,"completeRecordRate":1},{"region":"KEW","totalVolume":47037288,"rowCount":41440,"alarmCount":147569,"siteCount":117,"detectorCount":32,"averageDetectorVolume":1469915.25,"completeRecordRate":1},{"region":"CA2","totalVolume":46153112,"rowCount":38864,"alarmCount":71089,"siteCount":110,"detectorCount":32,"averageDetectorVolume":1442284.75,"completeRecordRate":1},{"region":"MNP","totalVolume":46139657,"rowCount":40544,"alarmCount":80182,"siteCount":116,"detectorCount":32,"averageDetectorVolume":1441864.28125,"completeRecordRate":1},{"region":"BRI","totalVolume":45009716,"rowCount":47132,"alarmCount":164014,"siteCount":134,"detectorCount":32,"averageDetectorVolume":1406553.625,"completeRecordRate":0.9999115958018614},{"region":"SK1","totalVolume":41679859,"rowCount":38080,"alarmCount":72010,"siteCount":108,"detectorCount":32,"averageDetectorVolume":1302495.59375,"completeRecordRate":1},{"region":"FT4","totalVolume":41498662,"rowCount":36424,"alarmCount":92060,"siteCount":111,"detectorCount":32,"averageDetectorVolume":1296833.1875,"completeRecordRate":0.9998029572992166},{"region":"MC1","totalVolume":39640715,"rowCount":48216,"alarmCount":72784,"siteCount":138,"detectorCount":32,"averageDetectorVolume":1238772.34375,"completeRecordRate":0.9985119047619048},{"region":"FR2","totalVolume":33484332,"rowCount":40992,"alarmCount":54944,"siteCount":110,"detectorCount":32,"averageDetectorVolume":1046385.375,"completeRecordRate":1},{"region":"BEN","totalVolume":25729460,"rowCount":34608,"alarmCount":58095,"siteCount":102,"detectorCount":32,"averageDetectorVolume":804045.625,"completeRecordRate":1},{"region":"DIO","totalVolume":11975753,"rowCount":18956,"alarmCount":79063,"siteCount":57,"detectorCount":32,"averageDetectorVolume":374242.28125,"completeRecordRate":1},{"region":"DUP","totalVolume":8143402,"rowCount":10864,"alarmCount":76346,"siteCount":30,"detectorCount":32,"averageDetectorVolume":254481.3125,"completeRecordRate":1},{"region":"MC3","totalVolume":5716721,"rowCount":8624,"alarmCount":4234,"siteCount":25,"detectorCount":32,"averageDetectorVolume":178647.53125,"completeRecordRate":1},{"region":"GE2","totalVolume":4183603,"rowCount":8512,"alarmCount":175345,"siteCount":21,"detectorCount":32,"averageDetectorVolume":130737.59375,"completeRecordRate":1},{"region":"VI2","totalVolume":3575709,"rowCount":3696,"alarmCount":2712,"siteCount":10,"detectorCount":32,"averageDetectorVolume":111740.90625,"completeRecordRate":1},{"region":"GR2","totalVolume":2405367,"rowCount":6384,"alarmCount":75918,"siteCount":17,"detectorCount":32,"averageDetectorVolume":75167.71875,"completeRecordRate":1},{"region":"MLT","totalVolume":1658217,"rowCount":6496,"alarmCount":200737,"siteCount":17,"detectorCount":32,"averageDetectorVolume":51819.28125,"completeRecordRate":1},{"region":"ML2","totalVolume":690623,"rowCount":2016,"alarmCount":32448,"siteCount":5,"detectorCount":32,"averageDetectorVolume":21581.96875,"completeRecordRate":1}]
